threedi_urban_eia_nl/__init__.py
threedi_urban_eia_nl/process_results.py
threedi_urban_eia_nl/rain_series_simulations.py
batch_calculator-0.0.1.dist-info/LICENSE
batch_calculator-0.0.1.dist-info/METADATA
batch_calculator-0.0.1.dist-info/WHEEL
batch_calculator-0.0.1.dist-info/entry_points.txt
batch_calculator-0.0.1.dist-info/top_level.txt
batch_calculator-0.0.1.dist-info/RECORD
