Metadata-Version: 2.1
Name: batch-calculator
Version: 0.0.1
Summary: 3Di batch calculations
Author-email: Daan van Ingen <daan.vaningen@nelen-schuurmans.nl>
License: MIT
Project-URL: Repository, https://github.com/nens/threedi-urban-eia-nl
Project-URL: Changelog, https://github.com/nens/threedi-urban-eia-nl/blob/master/CHANGES.rst
Classifier: Framework :: Django
Classifier: Programming Language :: Python
Classifier: License :: OSI Approved :: MIT License
License-File: LICENSE
Requires-Dist: click
Requires-Dist: netCDF4
Requires-Dist: pandas
Requires-Dist: threedi-api-client >=4.0.0
Requires-Dist: threedigrid >=1.0.16
Requires-Dist: numpy <2
Requires-Dist: SQLAlchemy
